veri_agents_knowledgebase/__init__.py
veri_agents_knowledgebase/knowledgebase.py
veri_agents_knowledgebase/types.py
veri_agents_knowledgebase/utils.py
veri_agents_knowledgebase/graphs/__init__.py
veri_agents_knowledgebase/graphs/extract.py
veri_agents_knowledgebase/graphs/qa.py
veri_agents_knowledgebase/lightrag/lightrag_kb.py
veri_agents_knowledgebase/lightrag/lightrag_tools.py
veri_agents_knowledgebase/qdrant/__init__.py
veri_agents_knowledgebase/qdrant/generic_kb.py
veri_agents_knowledgebase/qdrant/qdrant_doc_store.py
veri_agents_knowledgebase/qdrant/qdrant_kb.py
veri_agents_knowledgebase/qdrant/source_retriever.py
veri_agents_knowledgebase/qdrant/summarization.py
veri_agents_knowledgebase/qdrant/tests/qdrant_doc_store_test.py
veri_agents_knowledgebase/tools/__init__.py
veri_agents_knowledgebase/tools/knowledge_retrieval.py
veri_agents_knowledgebase-0.1.13.dist-info/METADATA
veri_agents_knowledgebase-0.1.13.dist-info/WHEEL
veri_agents_knowledgebase-0.1.13.dist-info/RECORD
