Metadata-Version: 2.4
Name: veri-agents-knowledgebase
Version: 0.1.13
Summary: Veritone Agents Toolkit: Knowledge bases
Author-email: Markus Toman <mtoman@veritone.com>, Teo Boley <tboley@veritone.com>
Requires-Python: >=3.12
Requires-Dist: cachetools>=5.5.2
Requires-Dist: veri-agents-common>=0.1.2
Provides-Extra: all
Requires-Dist: veri-agents-common[docling,fastembed,lightrag]>=0.1.2; extra == 'all'
Requires-Dist: veri-agents-common[docling,fastembed,qdrant]>=0.1.2; extra == 'all'
Requires-Dist: veri-agents-common[langgraph]>=0.1.2; extra == 'all'
Provides-Extra: dev
Requires-Dist: veri-agents-common[docling,fastembed,lightrag]>=0.1.2; extra == 'dev'
Requires-Dist: veri-agents-common[docling,fastembed,qdrant]>=0.1.2; extra == 'dev'
Requires-Dist: veri-agents-common[langgraph]>=0.1.2; extra == 'dev'
Provides-Extra: graphs
Requires-Dist: veri-agents-common[langgraph]>=0.1.2; extra == 'graphs'
Provides-Extra: lightrag
Requires-Dist: veri-agents-common[docling,fastembed,lightrag]>=0.1.2; extra == 'lightrag'
Provides-Extra: qdrant
Requires-Dist: veri-agents-common[docling,fastembed,qdrant]>=0.1.2; extra == 'qdrant'
